<?xml version="1.0" encoding="utf-8"?>
<TextureAtlas imagePath="Mr_Virtual_V2_Assets.png">
	<!-- Created using the Spritesheet and XML generator -->
	<!-- https://uncertainprod.github.io/FNF-Spritesheet-XML-generator-Web -->
	<SubTexture name="VDown0000" x="1672" y="4715" width="1702" height="722" frameX="2" frameY="-13" frameWidth="1698" frameHeight="832"/>
	<SubTexture name="VDown0001" x="2675" y="0" width="1680" height="826" frameX="-9" frameY="-8" frameWidth="1698" frameHeight="832"/>
	<SubTexture name="VDown0002" x="2675" y="0" width="1680" height="826" frameX="-9" frameY="-8" frameWidth="1698" frameHeight="832"/>
	<SubTexture name="VDown0003" x="2350" y="3579" width="1662" height="799" frameX="-17" frameY="0" frameWidth="1698" frameHeight="832"/>
	<SubTexture name="VDown0004" x="2350" y="3579" width="1662" height="799" frameX="-17" frameY="0" frameWidth="1698" frameHeight="832"/>
	<SubTexture name="VDown0005" x="0" y="4715" width="1672" height="772" frameX="-11" frameY="2" frameWidth="1698" frameHeight="832"/>
	<SubTexture name="VDown0006" x="0" y="4715" width="1672" height="772" frameX="-11" frameY="2" frameWidth="1698" frameHeight="832"/>
	<SubTexture name="VDown0007" x="0" y="4715" width="1672" height="772" frameX="-11" frameY="2" frameWidth="1698" frameHeight="832"/>
	<SubTexture name="VDown0008" x="0" y="4715" width="1672" height="772" frameX="-11" frameY="2" frameWidth="1698" frameHeight="832"/>
	<SubTexture name="VDown0009" x="0" y="4715" width="1672" height="772" frameX="-11" frameY="2" frameWidth="1698" frameHeight="832"/>
	<SubTexture name="VIdle0000" x="0" y="5487" width="835" height="1053" frameX="-3" frameY="-23" frameWidth="837" frameHeight="1077"/>
	<SubTexture name="VIdle0001" x="914" y="1828" width="839" height="1048" frameX="0" frameY="-28" frameWidth="837" frameHeight="1077"/>
	<SubTexture name="VIdle0002" x="914" y="1828" width="839" height="1048" frameX="0" frameY="-28" frameWidth="837" frameHeight="1077"/>
	<SubTexture name="VIdle0003" x="1793" y="1808" width="838" height="1051" frameX="2" frameY="-25" frameWidth="837" frameHeight="1077"/>
	<SubTexture name="VIdle0004" x="1793" y="1808" width="838" height="1051" frameX="2" frameY="-25" frameWidth="837" frameHeight="1077"/>
	<SubTexture name="VIdle0005" x="4355" y="2307" width="829" height="1069" frameX="0" frameY="-8" frameWidth="837" frameHeight="1077"/>
	<SubTexture name="VIdle0006" x="4355" y="2307" width="829" height="1069" frameX="0" frameY="-8" frameWidth="837" frameHeight="1077"/>
	<SubTexture name="VIdle0007" x="4355" y="2307" width="829" height="1069" frameX="0" frameY="-8" frameWidth="837" frameHeight="1077"/>
	<SubTexture name="VIdle0008" x="5525" y="2087" width="825" height="1078" frameX="-1" frameY="0" frameWidth="837" frameHeight="1077"/>
	<SubTexture name="VIdle0009" x="5525" y="2087" width="825" height="1078" frameX="-1" frameY="0" frameWidth="837" frameHeight="1077"/>
	<SubTexture name="VIdle0010" x="5525" y="2087" width="825" height="1078" frameX="-1" frameY="0" frameWidth="837" frameHeight="1077"/>
	<SubTexture name="VIdle0011" x="5525" y="3165" width="822" height="1081" frameX="-3" frameY="2" frameWidth="837" frameHeight="1077"/>
	<SubTexture name="VIdle0012" x="5525" y="3165" width="822" height="1081" frameX="-3" frameY="2" frameWidth="837" frameHeight="1077"/>
	<SubTexture name="VIdle0013" x="5525" y="3165" width="822" height="1081" frameX="-3" frameY="2" frameWidth="837" frameHeight="1077"/>
	<SubTexture name="VIdle0014" x="5525" y="3165" width="822" height="1081" frameX="-3" frameY="2" frameWidth="837" frameHeight="1077"/>
	<SubTexture name="VLeft0000" x="1177" y="3579" width="1173" height="1136" frameX="-2" frameY="-16" frameWidth="1173" frameHeight="1150"/>
	<SubTexture name="VLeft0001" x="0" y="3579" width="1177" height="1136" frameX="2" frameY="-16" frameWidth="1173" frameHeight="1150"/>
	<SubTexture name="VLeft0002" x="0" y="3579" width="1177" height="1136" frameX="2" frameY="-16" frameWidth="1173" frameHeight="1150"/>
	<SubTexture name="VLeft0003" x="4355" y="0" width="1170" height="1153" frameX="-4" frameY="1" frameWidth="1173" frameHeight="1150"/>
	<SubTexture name="VLeft0004" x="4355" y="0" width="1170" height="1153" frameX="-4" frameY="1" frameWidth="1173" frameHeight="1150"/>
	<SubTexture name="VLeft0005" x="4355" y="1153" width="1166" height="1154" frameX="-8" frameY="2" frameWidth="1173" frameHeight="1150"/>
	<SubTexture name="VLeft0006" x="4355" y="1153" width="1166" height="1154" frameX="-8" frameY="2" frameWidth="1173" frameHeight="1150"/>
	<SubTexture name="VLeft0007" x="4355" y="1153" width="1166" height="1154" frameX="-8" frameY="2" frameWidth="1173" frameHeight="1150"/>
	<SubTexture name="VLeft0008" x="4355" y="1153" width="1166" height="1154" frameX="-8" frameY="2" frameWidth="1173" frameHeight="1150"/>
	<SubTexture name="VLeft0009" x="4355" y="1153" width="1166" height="1154" frameX="-8" frameY="2" frameWidth="1173" frameHeight="1150"/>
	<SubTexture name="VLeft0010" x="4355" y="1153" width="1166" height="1154" frameX="-8" frameY="2" frameWidth="1173" frameHeight="1150"/>
	<SubTexture name="VLeft0011" x="4355" y="1153" width="1166" height="1154" frameX="-8" frameY="2" frameWidth="1173" frameHeight="1150"/>
	<SubTexture name="VLeft0012" x="4355" y="1153" width="1166" height="1154" frameX="-8" frameY="2" frameWidth="1173" frameHeight="1150"/>
	<SubTexture name="VLeft0013" x="4355" y="1153" width="1166" height="1154" frameX="-8" frameY="2" frameWidth="1173" frameHeight="1150"/>
	<SubTexture name="VLeft0014" x="4355" y="1153" width="1166" height="1154" frameX="-8" frameY="2" frameWidth="1173" frameHeight="1150"/>
	<SubTexture name="VRight0000" x="5525" y="1039" width="1264" height="1048" frameX="-43" frameY="2" frameWidth="1331" frameHeight="1045"/>
	<SubTexture name="VRight0001" x="5525" y="0" width="1275" height="1039" frameX="-35" frameY="-7" frameWidth="1331" frameHeight="1045"/>
	<SubTexture name="VRight0002" x="5525" y="0" width="1275" height="1039" frameX="-35" frameY="-7" frameWidth="1331" frameHeight="1045"/>
	<SubTexture name="VRight0003" x="2675" y="1864" width="1327" height="1035" frameX="0" frameY="-11" frameWidth="1331" frameHeight="1045"/>
	<SubTexture name="VRight0004" x="2675" y="1864" width="1327" height="1035" frameX="0" frameY="-11" frameWidth="1331" frameHeight="1045"/>
	<SubTexture name="VRight0005" x="2675" y="826" width="1334" height="1038" frameX="2" frameY="-8" frameWidth="1331" frameHeight="1045"/>
	<SubTexture name="VRight0006" x="2675" y="826" width="1334" height="1038" frameX="2" frameY="-8" frameWidth="1331" frameHeight="1045"/>
	<SubTexture name="VRight0007" x="2675" y="826" width="1334" height="1038" frameX="2" frameY="-8" frameWidth="1331" frameHeight="1045"/>
	<SubTexture name="VRight0008" x="2675" y="826" width="1334" height="1038" frameX="2" frameY="-8" frameWidth="1331" frameHeight="1045"/>
	<SubTexture name="VRight0009" x="2675" y="826" width="1334" height="1038" frameX="2" frameY="-8" frameWidth="1331" frameHeight="1045"/>
	<SubTexture name="VUp0000" x="1793" y="0" width="882" height="1808" frameX="-14" frameY="-19" frameWidth="910" frameHeight="1825"/>
	<SubTexture name="VUp0001" x="914" y="0" width="879" height="1828" frameX="-21" frameY="2" frameWidth="910" frameHeight="1825"/>
	<SubTexture name="VUp0002" x="914" y="0" width="879" height="1828" frameX="-21" frameY="2" frameWidth="910" frameHeight="1825"/>
	<SubTexture name="VUp0003" x="0" y="1779" width="898" height="1800" frameX="-14" frameY="-21" frameWidth="910" frameHeight="1825"/>
	<SubTexture name="VUp0004" x="0" y="1779" width="898" height="1800" frameX="-14" frameY="-21" frameWidth="910" frameHeight="1825"/>
	<SubTexture name="VUp0005" x="0" y="0" width="914" height="1779" frameX="2" frameY="-41" frameWidth="910" frameHeight="1825"/>
	<SubTexture name="VUp0006" x="0" y="0" width="914" height="1779" frameX="2" frameY="-41" frameWidth="910" frameHeight="1825"/>
	<SubTexture name="VUp0007" x="0" y="0" width="914" height="1779" frameX="2" frameY="-41" frameWidth="910" frameHeight="1825"/>
	<SubTexture name="VUp0008" x="0" y="0" width="914" height="1779" frameX="2" frameY="-41" frameWidth="910" frameHeight="1825"/>
	<SubTexture name="VUp0009" x="0" y="0" width="914" height="1779" frameX="2" frameY="-41" frameWidth="910" frameHeight="1825"/>
</TextureAtlas>